LICENSE
MANIFEST.in
README.rst
changelog
requirements.txt
setup.py
rfctools_common/__init__.py
rfctools_common/log.py
rfctools_common/parser.py
rfctools_common/test.py
rfctools_common/utils.py
rfctools_common.egg-info/PKG-INFO
rfctools_common.egg-info/SOURCES.txt
rfctools_common.egg-info/dependency_links.txt
rfctools_common.egg-info/not-zip-safe
rfctools_common.egg-info/requires.txt
rfctools_common.egg-info/top_level.txt
rfctools_common/templates/SVG-1.2-RFC.rng
rfctools_common/templates/rfc2629-other.ent
rfctools_common/templates/rfc2629-xhtml.ent
rfctools_common/templates/rfc2629.dtd
rfctools_common/templates/rfc7991.rng
rfctools_common/templates/svg-1.2-rfc.rng
rfctools_common/templates/svg.rng
rfctools_common/templates/v3.rng