Metadata-Version: 1.2
Name: rfctools-common
Version: 0.6.2
Summary: Common routines for a set of RFC Production center tools
Home-page: https://github.com/ietf-tools/RfcEditor/tree/master/rfctools_common
Author: Jim Schaad
Author-email: ietf@augustcellars.com
License: Simplified BSD
Keywords: RFC common
Platform: UNKNOWN
Classifier: Development Status :: 3 - Alpha
Classifier: Intended Audience :: Other Audience
Classifier: Topic :: Text Processing
Classifier: Topic :: Text Processing :: Markup :: XML
Classifier: License :: OSI Approved :: BSD License
Classifier: Programming Language :: Python :: 2.7
Classifier: Programming Language :: Python :: 3.7
Requires-Python: >=2.7, !=3.0.*, !=3.1.*, !=3.2.*, !=3.3.*, !=3.4.*, <4
